<annotation>
	<folder>White</folder>
	<filename>Romania_foto_765.jpg</filename>
	<path>/home/fantast/Price_tags/White/Romania_foto_765.jpg</path>
	<source>
		<database>Unknown</database>
	</source>
	<size>
		<width>864</width>
		<height>1152</height>
		<depth>3</depth>
	</size>
	<segmented>0</segmented>
	<object>
		<name>price_tag</name>
		<pose>Unspecified</pose>
		<truncated>0</truncated>
		<difficult>0</difficult>
		<bndbox>
			<xmin>2</xmin>
			<ymin>527</ymin>
			<xmax>856</xmax>
			<ymax>930</ymax>
		</bndbox>
	</object>
	<object>
		<name>product_name</name>
		<pose>Unspecified</pose>
		<truncated>0</truncated>
		<difficult>0</difficult>
		<bndbox>
			<xmin>17</xmin>
			<ymin>558</ymin>
			<xmax>468</xmax>
			<ymax>615</ymax>
		</bndbox>
	</object>
	<object>
		<name>product_id</name>
		<pose>Unspecified</pose>
		<truncated>0</truncated>
		<difficult>0</difficult>
		<bndbox>
			<xmin>82</xmin>
			<ymin>818</ymin>
			<xmax>232</xmax>
			<ymax>841</ymax>
		</bndbox>
	</object>
	<object>
		<name>price_lei</name>
		<pose>Unspecified</pose>
		<truncated>0</truncated>
		<difficult>0</difficult>
		<bndbox>
			<xmin>535</xmin>
			<ymin>621</ymin>
			<xmax>657</xmax>
			<ymax>878</ymax>
		</bndbox>
	</object>
	<object>
		<name>price_bani</name>
		<pose>Unspecified</pose>
		<truncated>0</truncated>
		<difficult>0</difficult>
		<bndbox>
			<xmin>652</xmin>
			<ymin>731</ymin>
			<xmax>820</xmax>
			<ymax>880</ymax>
		</bndbox>
	</object>
</annotation>
