<annotation>
	<folder>White</folder>
	<filename>Romania_foto_1060.jpg</filename>
	<path>/home/fantast/Price_tags/White/Romania_foto_1060.jpg</path>
	<source>
		<database>Unknown</database>
	</source>
	<size>
		<width>900</width>
		<height>1200</height>
		<depth>3</depth>
	</size>
	<segmented>0</segmented>
	<object>
		<name>price_tag</name>
		<pose>Unspecified</pose>
		<truncated>0</truncated>
		<difficult>0</difficult>
		<bndbox>
			<xmin>221</xmin>
			<ymin>376</ymin>
			<xmax>814</xmax>
			<ymax>855</ymax>
		</bndbox>
	</object>
	<object>
		<name>product_name</name>
		<pose>Unspecified</pose>
		<truncated>0</truncated>
		<difficult>0</difficult>
		<bndbox>
			<xmin>260</xmin>
			<ymin>437</ymin>
			<xmax>556</xmax>
			<ymax>466</ymax>
		</bndbox>
	</object>
	<object>
		<name>product_id</name>
		<pose>Unspecified</pose>
		<truncated>0</truncated>
		<difficult>0</difficult>
		<bndbox>
			<xmin>260</xmin>
			<ymin>789</ymin>
			<xmax>417</xmax>
			<ymax>820</ymax>
		</bndbox>
	</object>
	<object>
		<name>price_lei</name>
		<pose>Unspecified</pose>
		<truncated>0</truncated>
		<difficult>0</difficult>
		<bndbox>
			<xmin>560</xmin>
			<ymin>576</ymin>
			<xmax>658</xmax>
			<ymax>820</ymax>
		</bndbox>
	</object>
	<object>
		<name>price_bani</name>
		<pose>Unspecified</pose>
		<truncated>0</truncated>
		<difficult>0</difficult>
		<bndbox>
			<xmin>667</xmin>
			<ymin>687</ymin>
			<xmax>764</xmax>
			<ymax>820</ymax>
		</bndbox>
	</object>
</annotation>
